omi_cache_manager/__init__.py
omi_cache_manager/_decorators.py
omi_cache_manager/aio_redis_backend.py
omi_cache_manager/aio_redis_backend_py34.py
omi_cache_manager/aredis_backend.py
omi_cache_manager/async_cache_manager.py
omi_cache_manager/backends.py
omi_cache_manager-0.2.1.dist-info/METADATA
omi_cache_manager-0.2.1.dist-info/WHEEL
omi_cache_manager-0.2.1.dist-info/top_level.txt
omi_cache_manager-0.2.1.dist-info/RECORD
