Metadata-Version: 2.1
Name: omi-cache-manager
Version: 0.2.1
Summary: An async cache manager implemented with [asyncio] and backends
Home-page: https://github.com/limccn/omi_cache_manager
Author: limccn
Author-email: limccn@me.com
License: Apache License 2.0
Keywords: omi,cache_manager,asyncio,aredis,aio_redis
Platform: any
Requires-Dist: pydantic
